Tests/__init__.py
Tests/test_main.py
Tests/test_ns_search_saved_export.py
Tests/test_utils.py
ns_search_saved_export/__init__.py
ns_search_saved_export/ns_search_saved_export.py
ns_search_saved_export/utils.py
ns_search_saved_export-0.1.22.dist-info/LICENSE
ns_search_saved_export-0.1.22.dist-info/METADATA
ns_search_saved_export-0.1.22.dist-info/WHEEL
ns_search_saved_export-0.1.22.dist-info/top_level.txt
ns_search_saved_export-0.1.22.dist-info/RECORD
