Metadata-Version: 2.1
Name: ns_search_saved_export
Version: 0.1.22
Summary: A library for interacting with NetSuite API and exporting data
Home-page: https://github.com/gildder/netsuite-search-saved-export
Author: Gildder
Author-email: gildder@outlook.com
Classifier: Programming Language :: Python :: 3
Classifier: License :: OSI Approved :: MIT License
Classifier: Operating System :: OS Independent
Requires-Python: >=3.6
License-File: LICENSE
Requires-Dist: oauth2
Requires-Dist: requests
Requires-Dist: pandas
Requires-Dist: setuptools
Requires-Dist: openpyxl
